setup.py
src/strippers/__init__.py
src/strippers/wikipedia.py
strippers.wikipedia.egg-info/PKG-INFO
strippers.wikipedia.egg-info/SOURCES.txt
strippers.wikipedia.egg-info/dependency_links.txt
strippers.wikipedia.egg-info/namespace_packages.txt
strippers.wikipedia.egg-info/not-zip-safe
strippers.wikipedia.egg-info/requires.txt
strippers.wikipedia.egg-info/top_level.txt