Metadata-Version: 1.0
Name: strippers.wikipedia
Version: 0.3
Summary: Wikipedia(ja) article parser
Home-page: http://pypi.python.org/pypi/strippers.wikipedia
Author: Tomohiro Otsuka
Author-email: t.otsuka@gmail.com
License: LGPL
Keywords: Wikipedia
Platform: UNKNOWN
Classifier: Development Status :: 3 - Alpha
Classifier: Programming Language :: Python :: 2.6
Classifier: License :: OSI Approved :: GNU Library or Lesser General Public License (LGPL)
Classifier: Intended Audience :: Developers
Classifier: Topic :: Software Development :: Libraries :: Python Modules
Classifier: Operating System :: OS Independent
Classifier: Natural Language :: Japanese
